finalsa/dynamo/dao/__init__.py
finalsa/dynamo/dao/py.typed
finalsa/dynamo/dao/content/__init__.py
finalsa/dynamo/dao/content/base.py
finalsa/dynamo/dao/content/base_dao.py
finalsa/dynamo/dao/content/py.typed
finalsa_dynamo_dao-0.1.1.data/data/LICENSE.md
finalsa_dynamo_dao-0.1.1.dist-info/licenses/LICENSE.md
finalsa_dynamo_dao-0.1.1.dist-info/METADATA
finalsa_dynamo_dao-0.1.1.dist-info/WHEEL
finalsa_dynamo_dao-0.1.1.dist-info/top_level.txt
finalsa_dynamo_dao-0.1.1.dist-info/zip-safe
finalsa_dynamo_dao-0.1.1.dist-info/RECORD
